zepusu/__init__.py
zepusu-0.2.0.dist-info/LICENSE
zepusu-0.2.0.dist-info/METADATA
zepusu-0.2.0.dist-info/WHEEL
zepusu-0.2.0.dist-info/entry_points.txt
zepusu-0.2.0.dist-info/top_level.txt
zepusu-0.2.0.dist-info/RECORD
