Metadata-Version: 2.1
Name: zepusu
Version: 0.2.0
Summary: A minimalist ZeroMQ pub-sub command line client.
Home-page: https://gitlab.com/nvllsvm/zepusu
Author: Andrew Rabert
Author-email: ar@nullsum.net
License: MIT
Platform: UNKNOWN
Classifier: Development Status :: 3 - Alpha
Classifier: Programming Language :: Python :: 3 :: Only
Classifier: Programming Language :: Python :: 3.6
Classifier: Programming Language :: Python :: 3.7
Requires-Python: >=3.6
Requires-Dist: pyzmq
